midi_visualiser/main.py
midi_visualiser/piano_display.py
midi_visualiser/piano_display_settings.py
midi_visualiser/scrolling_note.py
midi_visualiser/song.py
midi_visualiser/visualiser.py
midi_visualiser/imgs/icon.png
midi_visualiser/imgs/pause.png
midi_visualiser/imgs/play.png
midi_visualiser/songs/0_pirates.mid
midi_visualiser/songs/1_moonlight_sonata.mid
midi_visualiser/songs/2_mii_channel.mid
midi_visualiser/songs/3_tetris.mid
midi_visualiser/songs/4_rush_e.mid
midi_visualiser/songs/5_all_star.mid
midi_visualiser/songs/6_maple_leaf_rag.mid
midi_visualiser/songs/7_clair_de_lune.mid
midi_visualiser/songs/8_fantaisie_impromptu.mid
midi_visualiser/songs/9_la_campanella.mid
midi_visualiser-0.1.10.dist-info/METADATA
midi_visualiser-0.1.10.dist-info/WHEEL
midi_visualiser-0.1.10.dist-info/entry_points.txt
midi_visualiser-0.1.10.dist-info/licenses/LICENSE
midi_visualiser-0.1.10.dist-info/RECORD
