Metadata-Version: 2.4
Name: midi-visualiser
Version: 0.1.10
Summary: A real-time MIDI player and visualiser built in Python.
Project-URL: Homepage, https://github.com/benjaminrall/midi-visualiser
Author-email: Benjamin Rall <benr2508@aol.com>
License-File: LICENSE
Classifier: License :: OSI Approved :: MIT License
Classifier: Operating System :: Microsoft :: Windows
Classifier: Programming Language :: Python :: 3
Requires-Python: >=3.12
Requires-Dist: argparse>=1.4.0
Requires-Dist: mido>=1.3.3
Requires-Dist: pygame>=2.6.1
